ricardoneud/api/client.py
ricardoneud/api/games.py
ricardoneud/api/oauth2.py
ricardoneud/api/reseller.py
ricardoneud/api/tools.py
ricardoneud/api/user.py
ricardoneud_api-1.2.0.dist-info/licenses/LICENSE.md
ricardoneud_api-1.2.0.dist-info/METADATA
ricardoneud_api-1.2.0.dist-info/WHEEL
ricardoneud_api-1.2.0.dist-info/top_level.txt
ricardoneud_api-1.2.0.dist-info/RECORD
