Metadata-Version: 2.4
Name: ricardoneud-api
Version: 1.2.0
Summary: Official Python SDK for the API from Ricardoneud.com
Author: Ricardoneud.com
License: MIT
Project-URL: Homepage, https://ricardoneud.com
Project-URL: Contact, https://ricardoneud.com/contact
Requires-Python: >=3.7
License-File: LICENSE.md
Requires-Dist: requests>=2.25.0
Dynamic: license-file
